{
  "nodes": [
    {
      "methodName": ".Example::main()",
      "sccId": 0,
      "uniqueSCCAndNoSelfLoop": true,
      "path": "example/Example.java:4",
      "bridge": false,
      "paramTypes": {

      },
      "kind": [
        "entry-point"
      ]
    },
    {
      "methodName": ".H::H()",
      "sccId": 6,
      "uniqueSCCAndNoSelfLoop": true,
      "path": "example/Example.java:0",
      "bridge": false,
      "paramTypes": {

      },
      "kind": [
        "constructor"
      ]
    },
    {
      "methodName": ".F::F()",
      "sccId": 7,
      "uniqueSCCAndNoSelfLoop": true,
      "path": "example/Example.java:0",
      "bridge": false,
      "paramTypes": {

      },
      "kind": [
        "constructor"
      ]
    },
    {
      "methodName": ".C::C()",
      "sccId": 8,
      "uniqueSCCAndNoSelfLoop": true,
      "path": "example/Example.java:0",
      "bridge": false,
      "paramTypes": {

      },
      "kind": [
        "constructor"
      ]
    },
    {
      "methodName": ".A::A()",
      "sccId": 11,
      "uniqueSCCAndNoSelfLoop": true,
      "path": "example/Example.java:0",
      "bridge": false,
      "paramTypes": {

      },
      "kind": [
        "constructor"
      ]
    },
    {
      "methodName": "java.lang.Object::<init>()",
      "sccId": 12,
      "uniqueSCCAndNoSelfLoop": true,
      "path": "jrt:/java.base/java/lang/Object.class:0",
      "bridge": false,
      "paramTypes": {

      },
      "kind": [
        "constructor"
      ]
    },
    {
      "methodName": ".C::clinit<>",
      "sccId": 9,
      "uniqueSCCAndNoSelfLoop": true,
      "path": "example/Example.java:47",
      "bridge": false,
      "paramTypes": {

      },
      "kind": [
        "static-initializer"
      ]
    },
    {
      "methodName": ".G::G()",
      "sccId": 10,
      "uniqueSCCAndNoSelfLoop": true,
      "path": "example/Example.java:0",
      "bridge": false,
      "paramTypes": {

      },
      "kind": [
        "constructor"
      ]
    },
    {
      "methodName": ".C::m()",
      "sccId": 5,
      "uniqueSCCAndNoSelfLoop": true,
      "path": "example/Example.java:48",
      "bridge": false,
      "paramTypes": {

      },
      "kind": [
        "method"
      ]
    },
    {
      "methodName": ".E::m()",
      "sccId": 4,
      "uniqueSCCAndNoSelfLoop": true,
      "path": "example/Example.java:38",
      "bridge": false,
      "paramTypes": {

      },
      "kind": [
        "method"
      ]
    },
    {
      "methodName": ".A::m()",
      "sccId": 3,
      "uniqueSCCAndNoSelfLoop": true,
      "path": "example/Example.java:60",
      "bridge": false,
      "paramTypes": {

      },
      "kind": [
        "method"
      ]
    },
    {
      "methodName": ".B::m()",
      "sccId": 2,
      "uniqueSCCAndNoSelfLoop": true,
      "path": "example/Example.java:54",
      "bridge": false,
      "paramTypes": {

      },
      "kind": [
        "method"
      ]
    },
    {
      "methodName": ".Example::bruh1()",
      "sccId": 1,
      "uniqueSCCAndNoSelfLoop": false,
      "path": "example/Example.java:14",
      "bridge": false,
      "paramTypes": {

      },
      "kind": [
        "method"
      ]
    },
    {
      "methodName": ".Example::bruh2()",
      "sccId": 1,
      "uniqueSCCAndNoSelfLoop": false,
      "path": "example/Example.java:18",
      "bridge": false,
      "paramTypes": {

      },
      "kind": [
        "method"
      ]
    },
    {
      "methodName": ".Example::bruh3()",
      "sccId": 1,
      "uniqueSCCAndNoSelfLoop": false,
      "path": "example/Example.java:22",
      "bridge": false,
      "paramTypes": {

      },
      "kind": [
        "method"
      ]
    }
  ],
  "edges": [
        {
      "source": ".Example::main()",
      "target": ".H::H()"
    }
   ,    {
      "source": ".Example::main()",
      "target": ".C::m()"
    }
   ,    {
      "source": ".Example::main()",
      "target": ".E::m()"
    }
   ,    {
      "source": ".Example::main()",
      "target": ".C::C()"
    }
   ,    {
      "source": ".Example::main()",
      "target": ".A::m()"
    }
   ,    {
      "source": ".Example::main()",
      "target": ".B::m()"
    }
   ,    {
      "source": ".Example::main()",
      "target": ".Example::bruh1()"
    }
   ,    {
      "source": ".H::H()",
      "target": ".F::F()"
    }
   ,    {
      "source": ".F::F()",
      "target": ".C::C()"
    }
   ,    {
      "source": ".C::C()",
      "target": ".A::A()"
    }
   ,    {
      "source": ".C::C()",
      "target": ".C::clinit<>"
    }
   ,    {
      "source": ".A::A()",
      "target": "java.lang.Object::<init>()"
    }
   ,    {
      "source": ".C::clinit<>",
      "target": ".G::G()"
    }
   ,    {
      "source": ".G::G()",
      "target": ".F::F()"
    }
   ,    {
      "source": ".Example::bruh1()",
      "target": ".Example::bruh2()"
    }
   ,    {
      "source": ".Example::bruh2()",
      "target": ".Example::bruh3()"
    }
   ,    {
      "source": ".Example::bruh3()",
      "target": ".Example::bruh1()"
    }
  ]
}
